nfkbin/model/scaler_model.pkl
nfkbin/model/svc_model_server
nfkbin/padel/Descriptors.xls
nfkbin/padel/PaDEL-Descriptor.jar
nfkbin/padel/nfkbin_descriptors.xml
nfkbin/padel/lib/ambit2-base-2.4.7-SNAPSHOT.jar
nfkbin/padel/lib/ambit2-core-2.4.7-SNAPSHOT.jar
nfkbin/padel/lib/ambit2-smarts-2.4.7-SNAPSHOT.jar
nfkbin/padel/lib/appframework-1.0.3.jar
nfkbin/padel/lib/cdk-1.4.15.jar
nfkbin/padel/lib/commons-cli-1.2.jar
nfkbin/padel/lib/guava-17.0.jar
nfkbin/padel/lib/jama.jar
nfkbin/padel/lib/jgrapht-0.6.0.jar
nfkbin/padel/lib/l2fprod-common-all.jar
nfkbin/padel/lib/libPaDEL-Descriptor.jar
nfkbin/padel/lib/libPaDEL-Jobs.jar
nfkbin/padel/lib/libPaDEL.jar
nfkbin/padel/lib/swing-worker-1.1.jar
nfkbin/padel/lib/vecmath1.2-1.14.jar
nfkbin/padel/lib/xom-1.1.jar
nfkbin/padel/license/LICENSE.txt
nfkbin/padel/license/README - CDK
nfkbin/padel/license/lgpl-2.1.txt
nfkbin/padel/license/lgpl.license
nfkbin/python_script/__init__.py
nfkbin/python_script/nfkbin.py
nfkbin-1.0.0.dist-info/METADATA
nfkbin-1.0.0.dist-info/WHEEL
nfkbin-1.0.0.dist-info/entry_points.txt
nfkbin-1.0.0.dist-info/top_level.txt
nfkbin-1.0.0.dist-info/RECORD
