Metadata-Version: 2.1
Name: nfkbin
Version: 1.0.0
Summary: NFkBin: Prediction of NF-Kbin
Author: Prof. G.P.S. Raghava
Author-email: raghava@iiitd.ac.in
Requires-Python: >=3.6
Requires-Dist: numpy
Requires-Dist: pandas
Requires-Dist: scikit-learn
Requires-Dist: argparse
Requires-Dist: tqdm
